xyztilefile/__init__.py
xyztilefile/xyzgeneric.py
xyztilefile/xyzgeojson.py
xyztilefile/xyzjson.py
xyztilefile/xyznpy.py
xyztilefile/xyzpickle.py
xyztilefile/xyzpng.py
xyztilefile/xyzsample.py
xyztilefile/xyzsample2.py
xyztilefile/xyztilefile.py
xyztilefile/xyztilemanager.py
xyztilefile/xyztxt.py
xyztilefile-0.3.3.dist-info/LICENSE
xyztilefile-0.3.3.dist-info/METADATA
xyztilefile-0.3.3.dist-info/WHEEL
xyztilefile-0.3.3.dist-info/top_level.txt
xyztilefile-0.3.3.dist-info/RECORD
