Metadata-Version: 2.1
Name: xyztilefile
Version: 0.3.3
Summary: manage files in xyz tile format
Author: Akito Davis Kawamura
License: MIT
Keywords: xyztilefile xyz-tile xyztile
Classifier: License :: OSI Approved :: MIT License
Classifier: Programming Language :: Python :: 3.9
License-File: LICENSE
Requires-Dist: numpy
Requires-Dist: scikit-image
Requires-Dist: geojson
